{"numero":"90","stations":[{"commune":"ANDELNANS","nom":"CORA ANDELNANS","adresse":"Route de montbeliard","marque":"CORA","cp":"90400","id":"90400001"},{"commune":"Beaucourt","nom":"AVIA BEAUCOURT","adresse":"37 rue alfred pechin","marque":"Avia","cp":"90500","id":"90500001"},{"commune":"BEAUCOURT","nom":"Super u beaucourt","adresse":"Rue alfred pechin","marque":"Systeme U","cp":"90500","id":"90500002"},{"commune":"Belfort","nom":"BELFI CENTRE E. LECLERC","adresse":"1 avenue du general de gaulle","marque":"Leclerc","cp":"90000","id":"90008001"},{"commune":"BELFORT","nom":"RELAIS BELFORT LECLERC","adresse":"56, avenue du general leclerc","marque":"Total Access","cp":"90000","id":"90000015"},{"commune":"BELFORT","nom":"RELAIS DES GLACIS","adresse":"Avenue d'altkirch","marque":"Total","cp":"90000","id":"90000013"},{"commune":"BELFORT","nom":"RELAIS DES GRANDS PRES","adresse":"65, faubourg de montbeliard","marque":"Total Access","cp":"90000","id":"90000014"},{"commune":"Belfort","nom":"SARL AMS AUTO","adresse":"4 faubourg de brisach","marque":"Total","cp":"90000","id":"90000002"},{"commune":"Belfort","nom":"STATION AVIA MAC AUTOMOBILE","adresse":"57 avenue d'altkirch","marque":"Avia","cp":"90000","id":"90000009"},{"commune":"BESSONCOURT","nom":"AUCHAN BESSONCOURT","adresse":"Cd 419","marque":"Auchan","cp":"90160","id":"90160001"},{"commune":"DELLE","nom":"INTERMARCHE DELLE","adresse":"37 faubourg de belfort","marque":"Intermarche","cp":"90100","id":"90100003"},{"commune":"Delle","nom":"station Avia","adresse":"62 faubourg de belfort","marque":"Avia","cp":"90100","id":"90100004"},{"commune":"GIROMAGNY","nom":"INTERMARCHE GIROMAGNY","adresse":"Zac du mont jean, faubourg d' alsace","marque":"Intermarche","cp":"90200","id":"90200002"},{"commune":"GIROMAGNY","nom":"Station tabac shop","adresse":"72 faubourg de belfort","marque":"Total","cp":"90200","id":"90200003"},{"commune":"MENONCOURT","nom":"SARL RELAIS DES 3 SAPINS","adresse":"Rue de la baume, rd83","marque":"Total","cp":"90150","id":"90150001"},{"commune":"Montreux-Chateau","nom":"019 DATS MONTREUX","adresse":"2 rue de la liberation","marque":"Coccinelle","cp":"90130","id":"90130001"},{"commune":"VALDOIE","nom":"SUPER U","adresse":"30, rue de turenne","marque":"Systeme U","cp":"90300","id":"90300002"}]}